{
  "Shadow": {
    "Drop Shadow": {
      "Lv2": {
        "color": {
          "value": "rgba(8, 18, 26, 0.12)"
        },
        "inset": {
          "value": false
        },
        "offset": {
          "x": {
            "value": 0
          },
          "y": {
            "value": 3.25
          }
        },
        "blurRadius": {
          "value": 3.875
        },
        "spreadRadius": {
          "value": 0
        }
      },
      "Lv4": {
        "color": {
          "value": "rgba(8, 18, 26, 0.12)"
        },
        "inset": {
          "value": false
        },
        "offset": {
          "x": {
            "value": 0
          },
          "y": {
            "value": 4.75
          }
        },
        "blurRadius": {
          "value": 7.125
        },
        "spreadRadius": {
          "value": 0
        }
      },
      "Lv6": {
        "color": {
          "value": "rgba(8, 18, 26, 0.12)"
        },
        "inset": {
          "value": false
        },
        "offset": {
          "x": {
            "value": 0
          },
          "y": {
            "value": 11
          }
        },
        "blurRadius": {
          "value": 14
        },
        "spreadRadius": {
          "value": 0
        }
      }
    }
  }
}